csadminlib/OAuth.py
csadminlib/__init__.py
csadminlib/get_ip.py
csadminlib/smtp.py
csadminlib-0.0.2.dist-info/LICENSE
csadminlib-0.0.2.dist-info/METADATA
csadminlib-0.0.2.dist-info/WHEEL
csadminlib-0.0.2.dist-info/top_level.txt
csadminlib-0.0.2.dist-info/RECORD
