Metadata-Version: 2.1
Name: csadminlib
Version: 0.0.2
Summary: A package containing functions that aid in server-side administative processes.
Home-page: https://github.com/tannerchase5/csadminlib
Author: Tanner Chase
Author-email: 49108373+tannerchase5@users.noreply.github.com
License: BSD 3 LICENSE
Project-URL: Bug Tracker, https://github.com/tannerchase5/csadminlib/issues
Platform: OS Independent
Classifier: Programming Language :: Python :: 3
Classifier: License :: OSI Approved :: BSD License
Classifier: Operating System :: OS Independent
Requires-Python: >=3.7
License-File: LICENSE
Requires-Dist: google-api-python-client (>=2.36.0)
Requires-Dist: google-auth-httplib2 (>=0.1.0)
Requires-Dist: google-auth-oauthlib (>=0.4.6)
Requires-Dist: httplib2 (>=0.20.4)
Requires-Dist: safety (>=1.10.3)
